linkspace-0.5.0.dist-info/METADATA
linkspace-0.5.0.dist-info/WHEEL
linkspace/__init__.py
linkspace/__init__.pyi
linkspace/py.typed
linkspace/linkspace.abi3.so
linkspace-0.5.0.dist-info/RECORD
