Metadata-Version: 2.1
Name: linkspace
Version: 0.5.0
Home-Page: https://www.linkspace.dev
Author: Anton Sol <AntonSol919@gmail.com>
Author-email: Anton Sol <AntonSol919@gmail.com>
License: MPL-2.0
Project-URL: Source Code, https://github.com/AntonSol919/linkspace
